itsimodels/__init__.py
itsimodels/correlation_search.py
itsimodels/deep_dive.py
itsimodels/entity_type.py
itsimodels/event_management_state.py
itsimodels/glass_table.py
itsimodels/glass_table_icon.py
itsimodels/glass_table_image.py
itsimodels/kpi_base_search.py
itsimodels/kpi_threshold_template.py
itsimodels/neap.py
itsimodels/service.py
itsimodels/service_analyzer.py
itsimodels/service_template.py
itsimodels/team.py
itsimodels/core/__init__.py
itsimodels/core/base_models.py
itsimodels/core/compat.py
itsimodels/core/field_decode.py
itsimodels/core/fields.py
itsimodels/core/migrators.py
itsimodels/core/setup_logging.py
tests/__init__.py
itsimodels-0.0.39.dist-info/LICENSE
itsimodels-0.0.39.dist-info/METADATA
itsimodels-0.0.39.dist-info/WHEEL
itsimodels-0.0.39.dist-info/top_level.txt
itsimodels-0.0.39.dist-info/RECORD
