Metadata-Version: 2.1
Name: itsimodels
Version: 0.0.39
Summary: Model Definitions for Splunk IT Service Intelligence
Home-page: https://github.com/splunk/itsi-models
Author: Splunk, Inc.
Classifier: Programming Language :: Python :: 2.7
Classifier: Programming Language :: Python :: 3
Classifier: License :: OSI Approved :: Apache Software License
Classifier: Operating System :: OS Independent
Requires-Python: >=2.7
License-File: LICENSE
